wat.py
wat_cli-0.1.3.dist-info/LICENSE
wat_cli-0.1.3.dist-info/METADATA
wat_cli-0.1.3.dist-info/WHEEL
wat_cli-0.1.3.dist-info/entry_points.txt
wat_cli-0.1.3.dist-info/top_level.txt
wat_cli-0.1.3.dist-info/RECORD
