Metadata-Version: 2.1
Name: wat-cli
Version: 0.1.3
Summary: Get short answers from Wolfram Alpha.
Home-page: http://github.com/phha/wat
Author: Philipp Hack
Author-email: philipp.hack@gmail.com
License: MIT
Platform: UNKNOWN
Classifier: Development Status :: 4 - Beta
Classifier: License :: OSI Approved :: MIT License
Classifier: Programming Language :: Python :: 3
Requires-Dist: click
Requires-Dist: click-config-file
Requires-Dist: requests
